parkocr/__init__.py
parkocr/backends.py
parkocr/detector.py
parkocr/models/yolov8n.onnx
parkocr-0.3.0.dist-info/licenses/LICENSE
parkocr-0.3.0.dist-info/METADATA
parkocr-0.3.0.dist-info/WHEEL
parkocr-0.3.0.dist-info/top_level.txt
parkocr-0.3.0.dist-info/RECORD
