Metadata-Version: 2.4
Name: parkocr
Version: 0.3.0
Summary: Automatic license plate recognition using YOLOv8 and EasyOCR, with ROI filtering, FIFO output, and screenshot support.
Author-email: João Luiz Thomazetti <joaoluizthomazetti@gmail.com>
License-Expression: MIT
Project-URL: Homepage, https://github.com/JoaoLuizThomazetti/parkocr
Project-URL: Repository, https://github.com/JoaoLuizThomazetti/parkocr
Project-URL: Issues, https://github.com/JoaoLuizThomazetti/parkocr/issues
Requires-Python: >=3.12
License-File: LICENSE
Requires-Dist: opencv-python
Requires-Dist: numpy
Provides-Extra: lite
Requires-Dist: onnxruntime>=1.16.0; extra == "lite"
Requires-Dist: rapidocr-onnxruntime>=1.3.0; extra == "lite"
Provides-Extra: full
Requires-Dist: easyocr>=1.7.0; extra == "full"
Requires-Dist: ultralytics>=8.0.0; extra == "full"
Provides-Extra: dev
Requires-Dist: pytest>=7.0.0; extra == "dev"
Requires-Dist: ruff>=0.1.0; extra == "dev"
Dynamic: license-file
